dpct/__init__.py
dpct/_nbdev.py
dpct/core.py
dpct-0.0.1.dist-info/LICENSE
dpct-0.0.1.dist-info/METADATA
dpct-0.0.1.dist-info/WHEEL
dpct-0.0.1.dist-info/entry_points.txt
dpct-0.0.1.dist-info/top_level.txt
dpct-0.0.1.dist-info/RECORD
